fuzzyparsers/__init__.py
fuzzyparsers/dates.py
fuzzyparsers/strings.py
fuzzyparsers-0.9.5.1.dist-info/COPYING
fuzzyparsers-0.9.5.1.dist-info/METADATA
fuzzyparsers-0.9.5.1.dist-info/WHEEL
fuzzyparsers-0.9.5.1.dist-info/top_level.txt
fuzzyparsers-0.9.5.1.dist-info/RECORD
