Metadata-Version: 2.1
Name: fuzzyparsers
Version: 0.9.5.1
Summary: A collection of free-form input parsers (with special focus on dates)
Home-page: https://github.com/jbmohler/fuzzyparsers
Author: Joel B. Mohler
Author-email: joel@kiwistrawberry.us
License: MIT
Platform: UNKNOWN
Classifier: Development Status :: 4 - Beta
Classifier: Intended Audience :: Developers
Classifier: License :: OSI Approved :: MIT License
Classifier: Programming Language :: Python :: 3
Classifier: Operating System :: OS Independent
